leasewebrestapi
