Metadata-Version: 2.1
Name: leasewebrestapi
Version: 0.2.22
Summary: Automate and Integrate your infrastructure with Leaseweb API.
Home-page: https://github.com/roman-bergman/LEASEWEB-REST-API
Author: Roman Bergman
Author-email: roman.bergman@protonmail.com
Maintainer: Roman Bergman
License: AGPL3.0
Platform: UNKNOWN
License-File: LICENSE
